html2mallard.py
html2mallard-0.2.2.data/data/man/man1/html2mallard.1
html2mallard-0.2.2.dist-info/LICENSE
html2mallard-0.2.2.dist-info/METADATA
html2mallard-0.2.2.dist-info/WHEEL
html2mallard-0.2.2.dist-info/entry_points.txt
html2mallard-0.2.2.dist-info/top_level.txt
html2mallard-0.2.2.dist-info/RECORD
