Metadata-Version: 2.1
Name: html2mallard
Version: 0.2.2
Summary: convert mkdocs´ html output to mallard/yelp xml
Home-page: https://fossil.include-once.org/modseccfg/wiki/html2mallard
License: Public Domain
Keywords: mkdocs mallard
Platform: UNKNOWN
Classifier: License :: Public Domain
Classifier: Topic :: Software Development :: Documentation
Requires-Python: >= 3.6
Requires-Dist: PyYAML (>=5.0)
